{
  "Abdusamad": {
    "name": "Abdusamad",
    "lastPrimaryHelp": null,
    "lastSecondaryHelp": null,
    "groupLockedUntil": 1763228454891,
    "totalHelped": 0,
    "clickHistory": []
  },
  "Taneem": {
    "name": "Taneem",
    "lastPrimaryHelp": null,
    "lastSecondaryHelp": null,
    "groupLockedUntil": 1763228454891,
    "totalHelped": 0,
    "clickHistory": []
  },
  "Zahra": {
    "name": "Zahra",
    "lastPrimaryHelp": null,
    "lastSecondaryHelp": null,
    "groupLockedUntil": 1763228454891,
    "totalHelped": 0,
    "clickHistory": []
  },
  "Siham": {
    "name": "Siham",
    "lastPrimaryHelp": null,
    "lastSecondaryHelp": null,
    "groupLockedUntil": 1763228454891,
    "totalHelped": 0,
    "clickHistory": []
  },
  "Ahlam": {
    "name": "Ahlam",
    "lastPrimaryHelp": 1763139296970,
    "lastSecondaryHelp": 1763214054891,
    "groupLockedUntil": null,
    "totalHelped": 1,
    "clickHistory": [
      {
        "type": "primary",
        "timestamp": 1763139296970,
        "date": "2025-11-14T16:54:56.970Z"
      },
      {
        "type": "secondary",
        "timestamp": 1763158205833,
        "date": "2025-11-14T22:10:05.833Z"
      },
      {
        "type": "secondary",
        "timestamp": 1763214048629,
        "date": "2025-11-15T13:40:48.629Z"
      },
      {
        "type": "secondary",
        "timestamp": 1763214051551,
        "date": "2025-11-15T13:40:51.551Z"
      },
      {
        "type": "secondary",
        "timestamp": 1763214054891,
        "date": "2025-11-15T13:40:54.891Z"
      }
    ]
  },
  "Mohamed": {
    "name": "Mohamed",
    "lastPrimaryHelp": null,
    "lastSecondaryHelp": null,
    "groupLockedUntil": 1763228454891,
    "totalHelped": 0,
    "clickHistory": []
  }
}